{"timestamp": "2024-09-18 02:20:39,576", "name": "BackblazeHandler", "level": "INFO", "message": "Image 'ATC_56671958-a8c1-451e-8835-f61fc10adc2c.jpg' uploaded successfully to Backblaze. URL: https://BeesAudio.s3.us-east-005.backblazeb2.com/ATC_56671958-a8c1-451e-8835-f61fc10adc2c.jpg", "pathname": "/home/runner/LotsOfBees/src/handlers/backblaze_handler.py", "lineno": 50, "funcName": "upload_image", "process": 1192, "thread": 140582288682560}
{"timestamp": "2024-09-21 00:55:02,696", "name": "BackblazeHandler", "level": "ERROR", "message": "Failed to upload image 'ATC_33de1588-8ca5-4f75-a838-ac1c36b9efd5.jpg' to Backblaze: An error occurred (InvalidAccessKeyId) when calling the PutObject operation: The key '005b2784557c8a40000000014' is not valid", "pathname": "/home/runner/workspace/src/handlers/backblaze_handler.py", "lineno": 53, "funcName": "upload_image", "process": 147, "thread": 139925810273856}
{"timestamp": "2024-09-21 01:01:50,341", "name": "BackblazeHandler", "level": "ERROR", "message": "Failed to upload image 'ATC_a84e5ed0-457a-4d20-ac69-faff27d3129f.jpg' to Backblaze: An error occurred (InvalidAccessKeyId) when calling the PutObject operation: The key '005b2784557c8a40000000014' is not valid", "pathname": "/home/runner/workspace/src/handlers/backblaze_handler.py", "lineno": 53, "funcName": "upload_image", "process": 147, "thread": 139925810273856}
{"timestamp": "2024-09-21 01:04:20,829", "name": "BackblazeHandler", "level": "INFO", "message": "Image 'ATC_133ae3ca-cb0b-4242-9ea1-ffbcb1dbe630.jpg' uploaded successfully to Backblaze. URL: https://galrocket.s3.us-east-005.backblazeb2.com/ATC_133ae3ca-cb0b-4242-9ea1-ffbcb1dbe630.jpg", "pathname": "/home/runner/workspace/src/handlers/backblaze_handler.py", "lineno": 50, "funcName": "upload_image", "process": 272, "thread": 139670200065600}
{"timestamp": "2024-09-21 01:17:56,052", "name": "BackblazeHandler", "level": "INFO", "message": "Image 'ATC_62ace04e-4eb4-4c57-965a-a1ac7f5b996d.jpg' uploaded successfully to Backblaze. URL: https://galrocket.s3.us-east-005.backblazeb2.com/ATC_62ace04e-4eb4-4c57-965a-a1ac7f5b996d.jpg", "pathname": "/home/runner/workspace/src/handlers/backblaze_handler.py", "lineno": 50, "funcName": "upload_image", "process": 342, "thread": 139914975735360}
{"timestamp": "2024-09-21 01:39:08,964", "name": "BackblazeHandler", "level": "INFO", "message": "Image 'ATC_bad28404-1545-4d52-9406-7fcd7d4c571c.jpg' uploaded successfully to Backblaze. URL: https://galrocket.s3.us-east-005.backblazeb2.com/ATC_bad28404-1545-4d52-9406-7fcd7d4c571c.jpg", "pathname": "/home/runner/workspace/src/handlers/backblaze_handler.py", "lineno": 50, "funcName": "upload_image", "process": 523, "thread": 140409749540416}
{"timestamp": "2024-09-21 01:49:49,782", "name": "BackblazeHandler", "level": "INFO", "message": "Image 'ATC_4d7b03e9-240f-4239-80d7-97d5b4241a99.jpg' uploaded successfully to Backblaze. URL: https://galrocket.s3.us-east-005.backblazeb2.com/ATC_4d7b03e9-240f-4239-80d7-97d5b4241a99.jpg", "pathname": "/home/runner/workspace/src/handlers/backblaze_handler.py", "lineno": 50, "funcName": "upload_image", "process": 630, "thread": 139802063498816}
{"timestamp": "2024-09-21 04:41:34,798", "name": "BackblazeHandler", "level": "INFO", "message": "Image 'ATC_b100ad5e-92a7-4ce6-af96-6d7b89b31939.jpg' uploaded successfully to Backblaze. URL: https://galrocket.s3.us-east-005.backblazeb2.com/ATC_b100ad5e-92a7-4ce6-af96-6d7b89b31939.jpg", "pathname": "/home/runner/workspace/src/handlers/backblaze_handler.py", "lineno": 50, "funcName": "upload_image", "process": 444, "thread": 140586995826240}
{"timestamp": "2024-09-21 05:03:31,059", "name": "BackblazeHandler", "level": "INFO", "message": "Image 'ATC_9e079083-8e9e-488b-a401-efe6bd7a0e8c.jpg' uploaded successfully to Backblaze. URL: https://galrocket.s3.us-east-005.backblazeb2.com/ATC_9e079083-8e9e-488b-a401-efe6bd7a0e8c.jpg", "pathname": "/home/runner/workspace/src/handlers/backblaze_handler.py", "lineno": 50, "funcName": "upload_image", "process": 1247, "thread": 140288585293376}
{"timestamp": "2024-09-21 05:10:11,669", "name": "BackblazeHandler", "level": "INFO", "message": "Image 'ATC_8103b686-d65e-4440-823b-cdc2e6abdb77.jpg' uploaded successfully to Backblaze. URL: https://galrocket.s3.us-east-005.backblazeb2.com/ATC_8103b686-d65e-4440-823b-cdc2e6abdb77.jpg", "pathname": "/home/runner/workspace/src/handlers/backblaze_handler.py", "lineno": 50, "funcName": "upload_image", "process": 1335, "thread": 140021910351424}
