{"timestamp": "2024-09-18 02:20:39,576", "name": "BackblazeHandler", "level": "INFO", "message": "Image 'ATC_56671958-a8c1-451e-8835-f61fc10adc2c.jpg' uploaded successfully to Backblaze. URL: https://BeesAudio.s3.us-east-005.backblazeb2.com/ATC_56671958-a8c1-451e-8835-f61fc10adc2c.jpg", "pathname": "/home/runner/LotsOfBees/src/handlers/backblaze_handler.py", "lineno": 50, "funcName": "upload_image", "process": 1192, "thread": 140582288682560}
{"timestamp": "2024-09-21 00:55:02,696", "name": "BackblazeHandler", "level": "ERROR", "message": "Failed to upload image 'ATC_33de1588-8ca5-4f75-a838-ac1c36b9efd5.jpg' to Backblaze: An error occurred (InvalidAccessKeyId) when calling the PutObject operation: The key '005b2784557c8a40000000014' is not valid", "pathname": "/home/runner/workspace/src/handlers/backblaze_handler.py", "lineno": 53, "funcName": "upload_image", "process": 147, "thread": 139925810273856}
{"timestamp": "2024-09-21 01:01:50,341", "name": "BackblazeHandler", "level": "ERROR", "message": "Failed to upload image 'ATC_a84e5ed0-457a-4d20-ac69-faff27d3129f.jpg' to Backblaze: An error occurred (InvalidAccessKeyId) when calling the PutObject operation: The key '005b2784557c8a40000000014' is not valid", "pathname": "/home/runner/workspace/src/handlers/backblaze_handler.py", "lineno": 53, "funcName": "upload_image", "process": 147, "thread": 139925810273856}
{"timestamp": "2024-09-21 01:04:20,829", "name": "BackblazeHandler", "level": "INFO", "message": "Image 'ATC_133ae3ca-cb0b-4242-9ea1-ffbcb1dbe630.jpg' uploaded successfully to Backblaze. URL: https://galrocket.s3.us-east-005.backblazeb2.com/ATC_133ae3ca-cb0b-4242-9ea1-ffbcb1dbe630.jpg", "pathname": "/home/runner/workspace/src/handlers/backblaze_handler.py", "lineno": 50, "funcName": "upload_image", "process": 272, "thread": 139670200065600}
{"timestamp": "2024-09-21 01:17:56,052", "name": "BackblazeHandler", "level": "INFO", "message": "Image 'ATC_62ace04e-4eb4-4c57-965a-a1ac7f5b996d.jpg' uploaded successfully to Backblaze. URL: https://galrocket.s3.us-east-005.backblazeb2.com/ATC_62ace04e-4eb4-4c57-965a-a1ac7f5b996d.jpg", "pathname": "/home/runner/workspace/src/handlers/backblaze_handler.py", "lineno": 50, "funcName": "upload_image", "process": 342, "thread": 139914975735360}
{"timestamp": "2024-09-21 01:39:08,964", "name": "BackblazeHandler", "level": "INFO", "message": "Image 'ATC_bad28404-1545-4d52-9406-7fcd7d4c571c.jpg' uploaded successfully to Backblaze. URL: https://galrocket.s3.us-east-005.backblazeb2.com/ATC_bad28404-1545-4d52-9406-7fcd7d4c571c.jpg", "pathname": "/home/runner/workspace/src/handlers/backblaze_handler.py", "lineno": 50, "funcName": "upload_image", "process": 523, "thread": 140409749540416}
{"timestamp": "2024-09-21 01:49:49,782", "name": "BackblazeHandler", "level": "INFO", "message": "Image 'ATC_4d7b03e9-240f-4239-80d7-97d5b4241a99.jpg' uploaded successfully to Backblaze. URL: https://galrocket.s3.us-east-005.backblazeb2.com/ATC_4d7b03e9-240f-4239-80d7-97d5b4241a99.jpg", "pathname": "/home/runner/workspace/src/handlers/backblaze_handler.py", "lineno": 50, "funcName": "upload_image", "process": 630, "thread": 139802063498816}
{"timestamp": "2024-09-21 04:41:34,798", "name": "BackblazeHandler", "level": "INFO", "message": "Image 'ATC_b100ad5e-92a7-4ce6-af96-6d7b89b31939.jpg' uploaded successfully to Backblaze. URL: https://galrocket.s3.us-east-005.backblazeb2.com/ATC_b100ad5e-92a7-4ce6-af96-6d7b89b31939.jpg", "pathname": "/home/runner/workspace/src/handlers/backblaze_handler.py", "lineno": 50, "funcName": "upload_image", "process": 444, "thread": 140586995826240}
{"timestamp": "2024-09-21 05:03:31,059", "name": "BackblazeHandler", "level": "INFO", "message": "Image 'ATC_9e079083-8e9e-488b-a401-efe6bd7a0e8c.jpg' uploaded successfully to Backblaze. URL: https://galrocket.s3.us-east-005.backblazeb2.com/ATC_9e079083-8e9e-488b-a401-efe6bd7a0e8c.jpg", "pathname": "/home/runner/workspace/src/handlers/backblaze_handler.py", "lineno": 50, "funcName": "upload_image", "process": 1247, "thread": 140288585293376}
{"timestamp": "2024-09-21 05:10:11,669", "name": "BackblazeHandler", "level": "INFO", "message": "Image 'ATC_8103b686-d65e-4440-823b-cdc2e6abdb77.jpg' uploaded successfully to Backblaze. URL: https://galrocket.s3.us-east-005.backblazeb2.com/ATC_8103b686-d65e-4440-823b-cdc2e6abdb77.jpg", "pathname": "/home/runner/workspace/src/handlers/backblaze_handler.py", "lineno": 50, "funcName": "upload_image", "process": 1335, "thread": 140021910351424}
{"timestamp": "2024-09-21 05:48:18,941", "name": "BackblazeHandler", "level": "INFO", "message": "Image 'ATC_1d1db1f2-6550-4e60-a800-d96dd2a39b7a.jpg' uploaded successfully to Backblaze. URL: https://galrocket.s3.us-east-005.backblazeb2.com/ATC_1d1db1f2-6550-4e60-a800-d96dd2a39b7a.jpg", "pathname": "/home/runner/workspace/src/handlers/backblaze_handler.py", "lineno": 50, "funcName": "upload_image", "process": 405, "thread": 139758208421440}
{"timestamp": "2024-09-21 05:53:46,308", "name": "BackblazeHandler", "level": "INFO", "message": "Image 'ATC_63cd6761-5c06-4e82-bef5-20fc0938781e.jpg' uploaded successfully to Backblaze. URL: https://galrocket.s3.us-east-005.backblazeb2.com/ATC_63cd6761-5c06-4e82-bef5-20fc0938781e.jpg", "pathname": "/home/runner/workspace/src/handlers/backblaze_handler.py", "lineno": 50, "funcName": "upload_image", "process": 555, "thread": 140393162161728}
{"timestamp": "2024-09-21 05:59:05,619", "name": "BackblazeHandler", "level": "INFO", "message": "Image 'ATC_f83b80e3-6f74-4706-ab14-b51789f728ac.jpg' uploaded successfully to Backblaze. URL: https://galrocket.s3.us-east-005.backblazeb2.com/ATC_f83b80e3-6f74-4706-ab14-b51789f728ac.jpg", "pathname": "/home/runner/workspace/src/handlers/backblaze_handler.py", "lineno": 50, "funcName": "upload_image", "process": 669, "thread": 140382081048128}
{"timestamp": "2024-09-22 14:35:34,615", "name": "BackblazeHandler", "level": "INFO", "message": "Image 'ATC_7caebb79-5575-4822-89bc-2a29adf619ca.jpg' uploaded successfully to Backblaze. URL: https://galrocket.s3.us-east-005.backblazeb2.com/ATC_7caebb79-5575-4822-89bc-2a29adf619ca.jpg", "pathname": "/home/runner/workspace/src/handlers/backblaze_handler.py", "lineno": 50, "funcName": "upload_image", "process": 258, "thread": 140476436127296}
{"timestamp": "2024-09-22 14:52:12,450", "name": "BackblazeHandler", "level": "INFO", "message": "Image 'ATC_45371c7b-9b7e-4aa4-a3d5-92af9ac5bc72.jpg' uploaded successfully to Backblaze. URL: https://galrocket.s3.us-east-005.backblazeb2.com/ATC_45371c7b-9b7e-4aa4-a3d5-92af9ac5bc72.jpg", "pathname": "/home/runner/workspace/src/handlers/backblaze_handler.py", "lineno": 50, "funcName": "upload_image", "process": 613, "thread": 139742296219200}
{"timestamp": "2024-09-22 16:20:39,576", "name": "BackblazeHandler", "level": "INFO", "message": "Initialized aioboto3 S3 client for BackblazeHandler.", "pathname": "/home/runner/workspace/src/handlers/backblaze_handler.py", "lineno": 59, "funcName": "initialize", "process": 433, "thread": 140580816322112}
{"timestamp": "2024-09-22 16:27:48,506", "name": "BackblazeHandler", "level": "INFO", "message": "Initialized aioboto3 S3 client for BackblazeHandler.", "pathname": "/home/runner/workspace/src/handlers/backblaze_handler.py", "lineno": 59, "funcName": "initialize", "process": 643, "thread": 139714401836608}
{"timestamp": "2024-09-22 16:30:05,480", "name": "BackblazeHandler", "level": "INFO", "message": "Initialized aioboto3 S3 client for BackblazeHandler.", "pathname": "/home/runner/workspace/src/handlers/backblaze_handler.py", "lineno": 59, "funcName": "initialize", "process": 738, "thread": 140244237147712}
{"timestamp": "2024-09-22 16:35:52,570", "name": "BackblazeHandler", "level": "INFO", "message": "Initialized aioboto3 S3 client for BackblazeHandler.", "pathname": "/home/runner/workspace/src/handlers/backblaze_handler.py", "lineno": 59, "funcName": "initialize", "process": 822, "thread": 140713165790784}
{"timestamp": "2024-09-22 16:58:05,756", "name": "BackblazeHandler", "level": "INFO", "message": "Initialized aioboto3 S3 client for BackblazeHandler.", "pathname": "/home/runner/workspace/src/handlers/backblaze_handler.py", "lineno": 59, "funcName": "initialize", "process": 1393, "thread": 140359413861952}
{"timestamp": "2024-09-22 17:22:23,414", "name": "BackblazeHandler", "level": "INFO", "message": "Initialized aioboto3 S3 client for BackblazeHandler.", "pathname": "/home/runner/workspace/src/handlers/backblaze_handler.py", "lineno": 59, "funcName": "initialize", "process": 2074, "thread": 140396518006336}
{"timestamp": "2024-09-22 17:26:30,960", "name": "BackblazeHandler", "level": "INFO", "message": "Initialized aioboto3 S3 client for BackblazeHandler.", "pathname": "/home/runner/workspace/src/handlers/backblaze_handler.py", "lineno": 59, "funcName": "initialize", "process": 2219, "thread": 139931456372288}
{"timestamp": "2024-09-22 17:29:32,694", "name": "BackblazeHandler", "level": "INFO", "message": "Initialized aioboto3 S3 client for BackblazeHandler.", "pathname": "/home/runner/workspace/src/handlers/backblaze_handler.py", "lineno": 59, "funcName": "initialize", "process": 2381, "thread": 140138250776128}
{"timestamp": "2024-09-22 17:35:49,019", "name": "BackblazeHandler", "level": "INFO", "message": "Initialized aioboto3 S3 client for BackblazeHandler.", "pathname": "/home/runner/workspace/src/handlers/backblaze_handler.py", "lineno": 59, "funcName": "initialize", "process": 2504, "thread": 139980196826688}
{"timestamp": "2024-09-22 17:46:55,335", "name": "BackblazeHandler", "level": "INFO", "message": "Initialized aioboto3 S3 client for BackblazeHandler.", "pathname": "/home/runner/workspace/src/handlers/backblaze_handler.py", "lineno": 59, "funcName": "initialize", "process": 2855, "thread": 139663689412160}
{"timestamp": "2024-09-22 17:48:41,837", "name": "BackblazeHandler", "level": "INFO", "message": "Initialized aioboto3 S3 client for BackblazeHandler.", "pathname": "/home/runner/workspace/src/handlers/backblaze_handler.py", "lineno": 59, "funcName": "initialize", "process": 2938, "thread": 140195513392704}
{"timestamp": "2024-09-22 18:02:27,605", "name": "BackblazeHandler", "level": "INFO", "message": "Initialized aioboto3 S3 client for BackblazeHandler.", "pathname": "/home/runner/workspace/src/handlers/backblaze_handler.py", "lineno": 59, "funcName": "initialize", "process": 3135, "thread": 140448130240064}
{"timestamp": "2024-09-22 18:05:40,537", "name": "BackblazeHandler", "level": "INFO", "message": "Image 'ATC_d0ca579f-cde6-477b-a669-389f598e595f.jpg' uploaded successfully to Backblaze. URL: https://galrocket.s3.us-east-005.backblazeb2.com/ATC_d0ca579f-cde6-477b-a669-389f598e595f.jpg", "pathname": "/home/runner/workspace/src/handlers/backblaze_handler.py", "lineno": 109, "funcName": "upload_image", "process": 3135, "thread": 140448130240064}
{"timestamp": "2024-09-22 18:07:35,941", "name": "BackblazeHandler", "level": "INFO", "message": "Initialized aioboto3 S3 client for BackblazeHandler.", "pathname": "/home/runner/workspace/src/handlers/backblaze_handler.py", "lineno": 59, "funcName": "initialize", "process": 3279, "thread": 140648959688256}
{"timestamp": "2024-09-22 18:16:22,744", "name": "BackblazeHandler", "level": "INFO", "message": "Initialized aioboto3 S3 client for BackblazeHandler.", "pathname": "/home/runner/workspace/src/handlers/backblaze_handler.py", "lineno": 59, "funcName": "initialize", "process": 3638, "thread": 140518158315072}
{"timestamp": "2024-09-22 18:17:00,646", "name": "BackblazeHandler", "level": "INFO", "message": "Image 'ATC_ce9cb120-5dcb-4792-ab15-ea65e550ae15.jpg' uploaded successfully to Backblaze. URL: https://galrocket.s3.us-east-005.backblazeb2.com/ATC_ce9cb120-5dcb-4792-ab15-ea65e550ae15.jpg", "pathname": "/home/runner/workspace/src/handlers/backblaze_handler.py", "lineno": 109, "funcName": "upload_image", "process": 3638, "thread": 140518158315072}
{"timestamp": "2024-09-22 18:23:25,072", "name": "BackblazeHandler", "level": "INFO", "message": "Initialized aioboto3 S3 client for BackblazeHandler.", "pathname": "/home/runner/workspace/src/handlers/backblaze_handler.py", "lineno": 59, "funcName": "initialize", "process": 3807, "thread": 140712408100416}
{"timestamp": "2024-09-22 18:23:59,140", "name": "BackblazeHandler", "level": "INFO", "message": "Image 'ATC_41250812-d565-4976-8754-4a63e38b6510.jpg' uploaded successfully to Backblaze. URL: https://galrocket.s3.us-east-005.backblazeb2.com/ATC_41250812-d565-4976-8754-4a63e38b6510.jpg", "pathname": "/home/runner/workspace/src/handlers/backblaze_handler.py", "lineno": 109, "funcName": "upload_image", "process": 3807, "thread": 140712408100416}
